dexpi/specificator/__init__.py
dexpi/specificator/command_line.py
dexpi/specificator/dsl_reader.py
dexpi/specificator/formatter.py
dexpi/specificator/enums_handling/__init__.py
dexpi/specificator/enums_handling/enums_reader.py
dexpi/specificator/formatters/rdf.py
dexpi/specificator/formatters/xmi.py
dexpi/specificator/formatters/xml.py
dexpi/specificator/formatters/html/__init__.py
dexpi/specificator/formatters/html/make.py
dexpi/specificator/formatters/pdf/__init__.py
dexpi/specificator/formatters/pdf/make.py
dexpi/specificator/sphinx_ext/__init__.py
dexpi/specificator/sphinx_ext/sp.css
dexpi/specificator/sphinx_ext/toc_tree.py
dexpi/specificator/test/__init__.py
dexpi/specificator/test/test_dependencies.py
dexpi/specificator/test/test_dsl_reader/__init__.py
dexpi/specificator/test/test_dsl_reader/test_error_messages.py
dexpi/specificator/uom_handling/__init__.py
dexpi/specificator/uom_handling/uom_reader.py
dexpi/specificator/utils/uml_diagrams.py
dexpi/specificator/utils/uml_diagrams_js/package-lock.json
dexpi/specificator/utils/uml_diagrams_js/package.json
dexpi/specificator/utils/uml_diagrams_js/run_elk.js
dexpi_specificator-0.9.dist-info/licenses/LICENSE
dexpi_specificator-0.9.dist-info/METADATA
dexpi_specificator-0.9.dist-info/WHEEL
dexpi_specificator-0.9.dist-info/top_level.txt
dexpi_specificator-0.9.dist-info/RECORD
