Metadata-Version: 2.4
Name: dexpi.specificator
Version: 0.9
Summary: Easy creation of engineering information models and related specification documents
Author: DEXPI e.V.
Classifier: Programming Language :: Python :: 3
Classifier: License :: OSI Approved :: MIT License
Classifier: Operating System :: OS Independent
Requires-Python: >=3.12
License-File: LICENSE
Requires-Dist: Sphinx==8.1.3
Requires-Dist: attrs==25.3.0
Requires-Dist: piccolo_theme==0.24.0
Requires-Dist: pnb.mcl==0.1.4
Requires-Dist: pyexcel-ezodf==0.3.4
Requires-Dist: tomlkit==0.13.2
Requires-Dist: Jinja2==3.1.6
Requires-Dist: MarkupSafe==3.0.2
Requires-Dist: Pygments==2.19.2
Requires-Dist: alabaster==1.0.0
Requires-Dist: babel==2.17.0
Requires-Dist: certifi==2025.8.3
Requires-Dist: charset-normalizer==3.4.3
Requires-Dist: colorama==0.4.6
Requires-Dist: docutils==0.21.2
Requires-Dist: idna==3.10
Requires-Dist: imagesize==1.4.1
Requires-Dist: lxml==5.4.0
Requires-Dist: packaging==25.0
Requires-Dist: pyparsing==3.2.3
Requires-Dist: rdflib==7.1.4
Requires-Dist: requests==2.32.5
Requires-Dist: snowballstemmer==3.0.1
Requires-Dist: sphinxcontrib-applehelp==2.0.0
Requires-Dist: sphinxcontrib-devhelp==2.0.0
Requires-Dist: sphinxcontrib-htmlhelp==2.1.0
Requires-Dist: sphinxcontrib-jsmath==1.0.1
Requires-Dist: sphinxcontrib-qthelp==2.0.0
Requires-Dist: sphinxcontrib-serializinghtml==2.0.0
Requires-Dist: urllib3==2.5.0
Dynamic: license-file
